MANIFEST.in
README.md
setup.py
MultiString.egg-info/PKG-INFO
MultiString.egg-info/SOURCES.txt
MultiString.egg-info/dependency_links.txt
MultiString.egg-info/top_level.txt
MultiString.egg-info/zip-safe
multistring/MultiString.py
multistring/__init__.py