Metadata-Version: 1.0
Name: MultiString
Version: 0.1.5
Summary: MultiString is a class that allows strings to take on different meanings depending on their context.
Home-page: http://www.github.com/tomthorogood/MultiString
Author: Tom A. Thorogood
Author-email: tom@tomthorogood.com
License: GPLv3
Platform: UNKNOWN
